README.md
setup.py
ipyumbrella/__init__.py
ipyumbrella.egg-info/PKG-INFO
ipyumbrella.egg-info/SOURCES.txt
ipyumbrella.egg-info/dependency_links.txt
ipyumbrella.egg-info/requires.txt
ipyumbrella.egg-info/top_level.txt
ipyumbrella/widgets/__init__.py
ipyumbrella/widgets/collection.py
ipyumbrella/widgets/output.py
ipyumbrella/widgets/styles.py
ipyumbrella/widgets/tags.py
ipyumbrella/widgets/util.py