Metadata-Version: 2.1
Name: ipyumbrella
Version: 0.0.29
Summary: Extended widgets for jupyter notebooks.
Home-page: https://github.com/beasteers/ipyumbrella
Author: Bea Steers
Author-email: bea.steers@gmail.com
License: MIT License
Platform: UNKNOWN
